adnex/__init__.py
adnex/computation.py
adnex/constraints.py
adnex/exceptions.py
adnex/model.py
adnex/transformation.py
adnex/variables.py
adnex/validation/__init__.py
adnex/validation/asserts.py
adnex/validation/core.py
adnex/validation/utils.py
adnex/validation/variables.py
adnex-0.1.0.dist-info/LICENSE
adnex-0.1.0.dist-info/METADATA
adnex-0.1.0.dist-info/WHEEL
adnex-0.1.0.dist-info/top_level.txt
adnex-0.1.0.dist-info/RECORD
