Metadata-Version: 2.1
Name: adnex
Version: 0.1.0
Summary: ADNEX model for predicting malignancy in adnexal masses.
Author-email: Filip Christiansen <filip.christiansen.2@ki.se>
License: MIT
Keywords: AI,ultrasound,ovarian cancer,diagnostics
Classifier: Programming Language :: Python :: 3
Classifier: License :: OSI Approved :: MIT License
Classifier: Operating System :: OS Independent
Requires-Python: >=3.8
License-File: LICENSE
Requires-Dist: numpy>=1.18
Requires-Dist: pandas>=1.0
Provides-Extra: dev
Requires-Dist: black; extra == "dev"
Requires-Dist: build; extra == "dev"
Requires-Dist: pre-commit; extra == "dev"
Requires-Dist: pytest; extra == "dev"
Requires-Dist: pytest-cov; extra == "dev"
Requires-Dist: twine; extra == "dev"
